letta_flask/__init__.py
letta_flask-0.1.1.dist-info/WHEEL
letta_flask-0.1.1.dist-info/METADATA
letta_flask-0.1.1.dist-info/RECORD
