Metadata-Version: 2.4
Name: letta-flask
Version: 0.1.1
Summary: A flask extension to build with Letta with ease
Requires-Python: >=3.10
Classifier: Framework :: Flask
Classifier: License :: OSI Approved :: MIT License
Classifier: Programming Language :: Python
Classifier: Typing :: Typed
Requires-Dist: flask>=3.1.0
Requires-Dist: letta-client>=0.1.67
Requires-Dist: pre-commit>=4.1.0
Requires-Dist: requests>=2.32.3
Requires-Dist: typing>=3.10.0.0
